clustering/__init__.py
clustering/kmeans.py
recommandations/__init__.py
CollectiveIntelligence-0.1.4.dist-info/LICENSE
CollectiveIntelligence-0.1.4.dist-info/METADATA
CollectiveIntelligence-0.1.4.dist-info/WHEEL
CollectiveIntelligence-0.1.4.dist-info/top_level.txt
CollectiveIntelligence-0.1.4.dist-info/RECORD
