Metadata-Version: 2.1
Name: CollectiveIntelligence
Version: 0.1.4
Summary: Collective Intelligence modules
Home-page: UNKNOWN
Author: 10fish
Author-email: ohth@sina.com
License: MIT
Project-URL: Homepage, http://github.com/10fish/CollectiveIntelligence
Project-URL: Source Code, http://github.com/10fish/CollectiveIntelligence
Platform: UNKNOWN
Classifier: Development Status :: 3 - Alpha
Classifier: License :: OSI Approved :: MIT License
Classifier: Programming Language :: Python :: 3
Classifier: Programming Language :: Python :: 3.7
Classifier: Topic :: Scientific/Engineering :: Artificial Intelligence
Requires-Dist: markdown
